exifproxy/_init_.py
exifproxy/exiftool.py
exifproxy/service.py
exifproxy/web.py
twisted/plugins/exiftool_proxy.py
exifproxy-1.0.1.dist-info/COPYING
exifproxy-1.0.1.dist-info/METADATA
exifproxy-1.0.1.dist-info/WHEEL
exifproxy-1.0.1.dist-info/top_level.txt
exifproxy-1.0.1.dist-info/RECORD
